napari_plugin_manager/__init__.py
napari_plugin_manager/_version.py
napari_plugin_manager/base_qt_package_installer.py
napari_plugin_manager/base_qt_plugin_dialog.py
napari_plugin_manager/npe2api.py
napari_plugin_manager/qt_package_installer.py
napari_plugin_manager/qt_plugin_dialog.py
napari_plugin_manager/qt_warning_dialog.py
napari_plugin_manager/qt_widgets.py
napari_plugin_manager/styles.qss
napari_plugin_manager/utils.py
napari_plugin_manager/_tests/__init__.py
napari_plugin_manager/_tests/conftest.py
napari_plugin_manager/_tests/test_base_installer_process.py
napari_plugin_manager/_tests/test_installer_process.py
napari_plugin_manager/_tests/test_npe2api.py
napari_plugin_manager/_tests/test_qt_plugin_dialog.py
napari_plugin_manager/_tests/test_utils.py
napari_plugin_manager-0.1.9.dist-info/licenses/LICENSE
napari_plugin_manager-0.1.9.dist-info/METADATA
napari_plugin_manager-0.1.9.dist-info/WHEEL
napari_plugin_manager-0.1.9.dist-info/top_level.txt
napari_plugin_manager-0.1.9.dist-info/RECORD
