Metadata-Version: 2.4
Name: napari-plugin-manager
Version: 0.1.9
Summary: Install plugins for napari, in napari.
Author-email: napari team <napari-steering-council@googlegroups.com>
License-Expression: BSD-3-Clause
Project-URL: homepage, https://github.com/napari/napari-plugin-manager
Classifier: Development Status :: 3 - Alpha
Classifier: Environment :: X11 Applications :: Qt
Classifier: Framework :: napari
Classifier: Intended Audience :: Education
Classifier: Intended Audience :: Science/Research
Classifier: Programming Language :: C
Classifier: Programming Language :: Python
Classifier: Programming Language :: Python :: 3 :: Only
Classifier: Programming Language :: Python :: 3.10
Classifier: Programming Language :: Python :: 3.11
Classifier: Programming Language :: Python :: 3.12
Classifier: Programming Language :: Python :: 3.13
Classifier: Topic :: Scientific/Engineering
Classifier: Topic :: Scientific/Engineering :: Visualization
Classifier: Topic :: Scientific/Engineering :: Information Analysis
Classifier: Topic :: Scientific/Engineering :: Bio-Informatics
Classifier: Topic :: Utilities
Classifier: Operating System :: Microsoft :: Windows
Classifier: Operating System :: POSIX
Classifier: Operating System :: Unix
Classifier: Operating System :: MacOS
Requires-Python: >=3.10
License-File: LICENSE
Requires-Dist: npe2
Requires-Dist: qtpy
Requires-Dist: superqt
Requires-Dist: pip
Requires-Dist: packaging
Provides-Extra: dev
Requires-Dist: PyQt6; extra == "dev"
Requires-Dist: pre-commit; extra == "dev"
Provides-Extra: uv
Requires-Dist: uv; extra == "uv"
Provides-Extra: testing
Requires-Dist: napari-plugin-manager[uv]; extra == "testing"
Requires-Dist: coverage; extra == "testing"
Requires-Dist: flaky; extra == "testing"
Requires-Dist: pytest; extra == "testing"
Requires-Dist: pytest-qt; extra == "testing"
Requires-Dist: virtualenv; extra == "testing"
Provides-Extra: docs
Requires-Dist: sphinx>6; extra == "docs"
Requires-Dist: sphinx-autobuild; extra == "docs"
Requires-Dist: sphinx-external-toc; extra == "docs"
Requires-Dist: sphinx-copybutton; extra == "docs"
Requires-Dist: sphinx-favicon; extra == "docs"
Requires-Dist: myst-nb; extra == "docs"
Requires-Dist: napari-sphinx-theme>=0.3.0; extra == "docs"
Dynamic: license-file
